s3_sync/__init__.py
s3_sync/__main__.py
s3_sync/__version__.py
s3_sync/cli/__init__.py
s3_sync/cli/cli.py
s3_sync/s3/__init__.py
s3_sync/s3/model.py
s3_sync/s3/sync.py
s3_sync/util/__init__.py
s3_sync/util/config.py
s3_sync/util/defaults.toml
s3_sync/util/helpers.py
s3_sync/util/logging.py
diskless_s3_sync-0.3.1.dist-info/LICENSE
diskless_s3_sync-0.3.1.dist-info/METADATA
diskless_s3_sync-0.3.1.dist-info/WHEEL
diskless_s3_sync-0.3.1.dist-info/entry_points.txt
diskless_s3_sync-0.3.1.dist-info/top_level.txt
diskless_s3_sync-0.3.1.dist-info/RECORD
