Metadata-Version: 2.2
Name: diskless-s3-sync
Version: 0.3.1
Summary: An tool to sync from one S3 bucket to another efficiently
Author-email: James Harmison <jharmison@redhat.com>
License: Copyright 2025 James Harmison <jharmison@redhat.com>
Project-URL: Source, https://github.com/jharmison-redhat/s3-sync
Project-URL: Documentation, https://github.com/jharmison-redhat/s3-sync
Classifier: License :: OSI Approved :: BSD License
Classifier: Operating System :: POSIX :: Linux
Requires-Python: >=3.11
License-File: LICENSE
Requires-Dist: dynaconf<3.3.0,>=3.2.6
Requires-Dist: pydantic<2.11.0,>=2.10.5
Requires-Dist: typer<0.16,>=0.15.1
Requires-Dist: boto3<1.36,>=1.35.97
Provides-Extra: dev
Requires-Dist: tox; extra == "dev"
Requires-Dist: pytest; extra == "dev"
Requires-Dist: types-boto3[boto3,s3]; extra == "dev"
